easystreaming/__init__.py
easystreaming/test.py
easystreaming-0.0.6.2.dist-info/LICENSE
easystreaming-0.0.6.2.dist-info/METADATA
easystreaming-0.0.6.2.dist-info/WHEEL
easystreaming-0.0.6.2.dist-info/top_level.txt
easystreaming-0.0.6.2.dist-info/RECORD
