Metadata-Version: 2.1
Name: easystreaming
Version: 0.0.6.2
Summary: A small Server and Client creator
Home-page: https://edugit.org/jakobkir/simplestreaming
Author: Jakob Kirsch
Author-email: jakob.kirsch@teckids.org
License: UNKNOWN
Platform: UNKNOWN
Classifier: Programming Language :: Python :: 3
Classifier: Operating System :: OS Independent
